pyleiden/__init__.py
pyleiden/pyleiden.py
pyleiden-0.1.2.dist-info/entry_points.txt
pyleiden-0.1.2.dist-info/LICENSE
pyleiden-0.1.2.dist-info/WHEEL
pyleiden-0.1.2.dist-info/METADATA
pyleiden-0.1.2.dist-info/RECORD
